_twisted_platform_support/portmap.so
_twisted_platform_support/__init__.py
_twisted_platform_support/sendmsg.c
_twisted_platform_support/sendmsg.so
_twisted_platform_support/_setup.py
_twisted_platform_support/portmap.c
_twisted_platform_support/_version.py
_twisted_platform_support/raiser.so
_twisted_platform_support/raiser/raiser.c
_twisted_platform_support/raiser/setup.py
_twisted_platform_support/raiser/raiser.pyx
_twisted_platform_support/iocp/wsarecv.pxi
_twisted_platform_support/iocp/notes.txt
_twisted_platform_support/iocp/acceptex.pxi
_twisted_platform_support/iocp/wsasend.pxi
_twisted_platform_support/iocp/winsock_pointers.h
_twisted_platform_support/iocp/iocpsupport.pyx
_twisted_platform_support/iocp/iocpsupport.c
_twisted_platform_support/iocp/winsock_pointers.c
_twisted_platform_support/iocp/setup.py
_twisted_platform_support/iocp/build.bat
_twisted_platform_support/iocp/connectex.pxi
_twisted_platform_support/test/__init__.py
_twisted_platform_support/test/test_setup.py
_twisted_platform_support/test/test_api.py
twisted_platform_support-16.12.3.dist-info/WHEEL
twisted_platform_support-16.12.3.dist-info/DESCRIPTION.rst
twisted_platform_support-16.12.3.dist-info/METADATA
twisted_platform_support-16.12.3.dist-info/RECORD
twisted_platform_support-16.12.3.dist-info/top_level.txt
twisted_platform_support-16.12.3.dist-info/metadata.json
