Metadata-Version: 2.0
Name: twisted-platform-support
Version: 16.12.3
Summary: Platform support packages for Twisted.
Home-page: https://github.com/twisted/twisted_platform_support
Author: Amber Brown
Author-email: hawkowl@twistedmatrix.com
License: MIT
Platform: UNKNOWN
Classifier: Intended Audience :: Developers
Classifier: License :: OSI Approved :: MIT License
Classifier: Programming Language :: Python :: 2
Classifier: Programming Language :: Python :: 2.7
Classifier: Programming Language :: Python :: 3
Classifier: Programming Language :: Python :: 3.3
Classifier: Programming Language :: Python :: 3.4
Classifier: Programming Language :: Python :: 3.5
